PyGUIBuilder/PyGUIBuilder.dll
PyGUIBuilder/__init__.py
PyGUIBuilder/main.py
PyGUIBuilder-1.5.dist-info/LICENSE
PyGUIBuilder-1.5.dist-info/METADATA
PyGUIBuilder-1.5.dist-info/WHEEL
PyGUIBuilder-1.5.dist-info/top_level.txt
PyGUIBuilder-1.5.dist-info/RECORD
