Metadata-Version: 2.1
Name: PyGUIBuilder
Version: 1.5
Summary: A simple library for creating GUI applications
Home-page: https://github.com/ArtemP36/PyGUIBuilder
Author: Artem Panov
Author-email: panovartem690@gmail.com
License: MIT License
Requires-Python: >=3.10
License-File: LICENSE
